Pollcord/__init__.py
Pollcord/client.py
Pollcord/error.py
Pollcord/poll.py
pollcord-0.1b1.dist-info/licenses/LICENSE
pollcord-0.1b1.dist-info/METADATA
pollcord-0.1b1.dist-info/WHEEL
pollcord-0.1b1.dist-info/top_level.txt
pollcord-0.1b1.dist-info/RECORD
