Metadata-Version: 2.4
Name: Pollcord
Version: 0.1b1
Summary: Async Python wrapper for Discord's native polling API.
Author-email: Myst1cS04p <myst1cs04p@gmail.com>
License: MIT
Project-URL: Homepage, https://github.com/Myst1cS04p/Pollcord
Project-URL: Repository, https://github.com/Myst1cS04p/Pollcord
Keywords: discord,polls,polling,discord-api,asyncio
Classifier: Development Status :: 4 - Beta
Classifier: Intended Audience :: Developers
Classifier: License :: OSI Approved :: MIT License
Classifier: Programming Language :: Python :: 3
Classifier: Programming Language :: Python :: 3.9
Classifier: Programming Language :: Python :: 3.10
Classifier: Programming Language :: Python :: 3.11
Classifier: Topic :: Software Development :: Libraries
Requires-Python: >=3.9
License-File: LICENSE
Requires-Dist: aiohttp>=3.8
Dynamic: license-file
